id/__init__.py
id/__main__.py
id/py.typed
id/_internal/oidc/__init__.py
id/_internal/oidc/ambient.py
id-1.6.0.dist-info/entry_points.txt
id-1.6.0.dist-info/licenses/LICENSE
id-1.6.0.dist-info/WHEEL
id-1.6.0.dist-info/METADATA
id-1.6.0.dist-info/RECORD
