Metadata-Version: 2.4
Name: id
Version: 1.6.0
Summary: A tool for generating OIDC identities
Requires-Python: >=3.9
Classifier: License :: OSI Approved :: Apache Software License
Classifier: Programming Language :: Python :: 3 :: Only
Classifier: Programming Language :: Python :: 3
Classifier: Programming Language :: Python :: 3.9
Classifier: Programming Language :: Python :: 3.10
Classifier: Programming Language :: Python :: 3.11
Classifier: Programming Language :: Python :: 3.12
Classifier: Programming Language :: Python :: 3.13
Classifier: Programming Language :: Python :: 3.14
Classifier: Development Status :: 5 - Production/Stable
Classifier: Intended Audience :: Developers
Classifier: Topic :: Security
Classifier: Topic :: Security :: Cryptography
License-File: LICENSE
Requires-Dist: urllib3 >= 2, < 3
Requires-Dist: build ; extra == "dev"
Requires-Dist: bump >= 1.3.2 ; extra == "dev"
Requires-Dist: id[test, lint] ; extra == "dev"
Requires-Dist: bandit ; extra == "lint"
Requires-Dist: interrogate ; extra == "lint"
Requires-Dist: mypy ; extra == "lint"
Requires-Dist: ruff < 0.14.3 ; extra == "lint"
Requires-Dist: pytest ; extra == "test"
Requires-Dist: pytest-cov ; extra == "test"
Requires-Dist: pretend ; extra == "test"
Requires-Dist: coverage[toml] ; extra == "test"
Project-URL: Homepage, https://pypi.org/project/id/
Project-URL: Issues, https://github.com/di/id/issues
Project-URL: Source, https://github.com/di/id
Provides-Extra: dev
Provides-Extra: lint
Provides-Extra: test
